[{"tipo": "1986 gasolina", "valor": "4317"}, {"tipo": "1987 gasolina", "valor": "4482"}, {"tipo": "1988 gasolina", "valor": "4635"}, {"tipo": "1989 gasolina", "valor": "5659"}, {"tipo": "1990 gasolina", "valor": "5963"}, {"tipo": "1991 gasolina", "valor": "6750"}, {"tipo": "1992 gasolina", "valor": "7141"}, {"tipo": "1993 gasolina", "valor": "8402"}, {"tipo": "1994 gasolina", "valor": "8771"}, {"tipo": "2003 gasolina", "valor": "13277"}, {"tipo": "2004 gasolina", "valor": "13934"}, {"tipo": "2005 gasolina", "valor": "14777"}, {"tipo": "2006 gasolina", "valor": "15250"}, {"tipo": "2007 gasolina", "valor": "16694"}, {"tipo": "2008 gasolina", "valor": "17480"}, {"tipo": "2009 gasolina", "valor": "19669"}, {"tipo": "2010 gasolina", "valor": "20388"}, {"tipo": "2011 gasolina", "valor": "21337"}, {"tipo": "2012 gasolina", "valor": "24083"}, {"tipo": "2013 gasolina", "valor": "26529"}]