[{"tipo": "1990 gasolina", "valor": "5381"}, {"tipo": "1991 gasolina", "valor": "5657"}, {"tipo": "1992 gasolina", "valor": "5896"}, {"tipo": "1993 gasolina", "valor": "6455"}, {"tipo": "1994 gasolina", "valor": "6794"}, {"tipo": "1995 gasolina", "valor": "7215"}, {"tipo": "1995 \u00e1lcool", "valor": "6581"}, {"tipo": "1996 gasolina", "valor": "7449"}, {"tipo": "1996 \u00e1lcool", "valor": "7179"}, {"tipo": "1997 gasolina", "valor": "8762"}, {"tipo": "1997 \u00e1lcool", "valor": "8004"}, {"tipo": "1998 \u00e1lcool", "valor": "8625"}]