[{"tipo": "1985 gasolina", "valor": "9545"}, {"tipo": "1986 gasolina", "valor": "10013"}, {"tipo": "1987 gasolina", "valor": "11424"}, {"tipo": "1988 gasolina", "valor": "12411"}, {"tipo": "1989 gasolina", "valor": "12990"}, {"tipo": "1990 gasolina", "valor": "14820"}, {"tipo": "1991 gasolina", "valor": "15642"}, {"tipo": "1992 gasolina", "valor": "16234"}, {"tipo": "1993 gasolina", "valor": "18151"}, {"tipo": "1994 gasolina", "valor": "20010"}, {"tipo": "1995 gasolina", "valor": "20721"}, {"tipo": "1996 gasolina", "valor": "22418"}]