[{"tipo": "2007 gasolina", "valor": "79474"}, {"tipo": "2008 gasolina", "valor": "89559"}, {"tipo": "2009 gasolina", "valor": "93390"}, {"tipo": "2010 gasolina", "valor": "98474"}, {"tipo": "2011 gasolina", "valor": "110258"}, {"tipo": "2012 gasolina", "valor": "115287"}, {"tipo": "2013 gasolina", "valor": "129995"}, {"tipo": "2014 gasolina", "valor": "142186"}, {"tipo": "2015 gasolina", "valor": "167341"}, {"tipo": "2016 gasolina", "valor": "185105"}, {"tipo": "2017 gasolina", "valor": "206306"}, {"tipo": "2018 gasolina", "valor": "226468"}, {"tipo": "Zero km gasolina", "valor": "262052"}]