[{"tipo": "1993 gasolina", "valor": "8661"}, {"tipo": "1994 gasolina", "valor": "10328"}, {"tipo": "1995 gasolina", "valor": "11149"}, {"tipo": "1996 gasolina", "valor": "12142"}, {"tipo": "1997 gasolina", "valor": "13994"}, {"tipo": "1998 gasolina", "valor": "15964"}, {"tipo": "1999 gasolina", "valor": "16648"}, {"tipo": "2000 gasolina", "valor": "17489"}, {"tipo": "2001 gasolina", "valor": "18044"}, {"tipo": "2002 gasolina", "valor": "21554"}, {"tipo": "2003 gasolina", "valor": "22742"}, {"tipo": "2005 gasolina", "valor": "23682"}]