[{"tipo": "1994 gasolina", "valor": "9914"}, {"tipo": "1995 gasolina", "valor": "10261"}, {"tipo": "1996 gasolina", "valor": "11236"}, {"tipo": "1997 gasolina", "valor": "11745"}, {"tipo": "1998 gasolina", "valor": "12119"}, {"tipo": "1999 gasolina", "valor": "12525"}, {"tipo": "2000 gasolina", "valor": "12956"}, {"tipo": "2001 gasolina", "valor": "13352"}, {"tipo": "2002 gasolina", "valor": "13845"}, {"tipo": "2003 gasolina", "valor": "14302"}, {"tipo": "2004 gasolina", "valor": "14785"}, {"tipo": "2005 gasolina", "valor": "15276"}, {"tipo": "2006 gasolina", "valor": "16379"}, {"tipo": "2007 gasolina", "valor": "16924"}, {"tipo": "2008 gasolina", "valor": "17488"}, {"tipo": "2009 gasolina", "valor": "18202"}]