[{"tipo": "1999 gasolina", "valor": "12894"}, {"tipo": "2000 gasolina", "valor": "16103"}, {"tipo": "2001 gasolina", "valor": "16854"}, {"tipo": "2002 gasolina", "valor": "17887"}, {"tipo": "2003 gasolina", "valor": "18522"}, {"tipo": "2004 gasolina", "valor": "19353"}, {"tipo": "2005 gasolina", "valor": "20555"}, {"tipo": "2006 gasolina", "valor": "21594"}, {"tipo": "2007 gasolina", "valor": "22751"}, {"tipo": "2008 gasolina", "valor": "23984"}, {"tipo": "2009 gasolina", "valor": "28838"}, {"tipo": "2010 gasolina", "valor": "32867"}, {"tipo": "2011 gasolina", "valor": "36807"}, {"tipo": "2013 gasolina", "valor": "39617"}, {"tipo": "2014 gasolina", "valor": "40865"}]